ifctruss/__init__.py
ifctruss/_calfem.py
ifctruss/_direct_stiffness_method.py
ifctruss/_example.py
ifctruss/_modidx.py
ifctruss/_save_result.py
ifctruss/_structural_analysis_model.py
ifctruss/_truss_creation.py
ifctruss/_view.py
ifctruss/ifctruss.py
ifctruss/solver.py
ifctruss-0.1.4.dist-info/COPYING
ifctruss-0.1.4.dist-info/COPYING.LESSER
ifctruss-0.1.4.dist-info/METADATA
ifctruss-0.1.4.dist-info/WHEEL
ifctruss-0.1.4.dist-info/entry_points.txt
ifctruss-0.1.4.dist-info/top_level.txt
ifctruss-0.1.4.dist-info/RECORD
