Metadata-Version: 2.1
Name: ifctruss
Version: 0.1.4
Summary: Create and calculate trusses in IFC's
Home-page: https://github.com/IfcTruss/IfcTruss
Author: IfcTruss Contributors
Author-email: ifctruss@mailbox.org
License: GNU Lesser General Public License v3
Keywords: ifc truss python
Classifier: Development Status :: 4 - Beta
Classifier: Intended Audience :: Developers
Classifier: Natural Language :: English
Classifier: Programming Language :: Python :: 3.11
Classifier: License :: OSI Approved :: GNU Lesser General Public License v3 or later (LGPLv3+)
Requires-Python: >=3.11
License-File: COPYING
License-File: COPYING.LESSER
Requires-Dist: fastcore
Requires-Dist: ifcopenshell
Requires-Dist: lark
Requires-Dist: numpy >=1.24.4
Requires-Dist: pandas
Provides-Extra: calfem
Requires-Dist: calfem-python-small ; extra == 'calfem'
Provides-Extra: dev
Requires-Dist: Jinja2 ; extra == 'dev'
Requires-Dist: Pyarrow ; extra == 'dev'
Requires-Dist: calfem-python-small ; extra == 'dev'
Requires-Dist: odfpy ; extra == 'dev'
Requires-Dist: openpyxl ; extra == 'dev'
Requires-Dist: rich ; extra == 'dev'
Provides-Extra: ods
Requires-Dist: odfpy ; extra == 'ods'
Provides-Extra: xlsx
Requires-Dist: openpyxl ; extra == 'xlsx'
